fileflix/__init__.py
fileflix/core.py
fileflix-0.1.3.dist-info/licenses/LICENSE
fileflix-0.1.3.dist-info/METADATA
fileflix-0.1.3.dist-info/WHEEL
fileflix-0.1.3.dist-info/top_level.txt
fileflix-0.1.3.dist-info/RECORD
