Metadata-Version: 2.4
Name: fileflix
Version: 0.1.3
Summary: A simple package to read and write multiple file formats with one function
Home-page: https://github.com/Suryavanshii/fileflix
Author: Rajkumar Suryavanshi
Author-email: krajsuryaaa@gmail.com
Classifier: Programming Language :: Python :: 3
Classifier: License :: OSI Approved :: MIT License
Classifier: Operating System :: OS Independent
Requires-Python: >=3.7
License-File: LICENSE
Requires-Dist: pandas
Requires-Dist: openpyxl
Requires-Dist: pyarrow
Dynamic: author
Dynamic: author-email
Dynamic: classifier
Dynamic: home-page
Dynamic: license-file
Dynamic: requires-dist
Dynamic: requires-python
Dynamic: summary
